qat/bind/qlmaas_AccountManager_client.so
qat/bind/qlmaas_QLMHelpers_client.so
qat/bind/qlmaas_Scheduler_client.so
qat/comm/asynchronous/__init__.so
qat/comm/asynchronous/constants.so
qat/comm/asynchronous/ttypes.so
qat/comm/qlmaas/AccountManager.so
qat/comm/qlmaas/QLMHelpers.so
qat/comm/qlmaas/Scheduler.so
qat/comm/qlmaas/__init__.so
qat/comm/qlmaas/_ttypes.so
qat/comm/qlmaas/constants.so
qat/comm/qlmaas/ttypes.so
qat/qlmaas/__init__.so
qat/qlmaas/actions.so
qat/qlmaas/applications.so
qat/qlmaas/async_batch.so
qat/qlmaas/commands.so
qat/qlmaas/connection.so
qat/qlmaas/crypto.so
qat/qlmaas/generators.so
qat/qlmaas/https.so
qat/qlmaas/log_utils.so
qat/qlmaas/plugins.so
qat/qlmaas/prompt.so
qat/qlmaas/proxy.so
qat/qlmaas/qpus.so
qat/qlmaas/remoteobjects.so
qat/qlmaas/remoteservice.so
qat/qlmaas/remotestack.so
qat/qlmaas/result.so
qat/qlmaas/tools.so
qat/qlmaas/upload.so
qat/qlmaas/version.so
qat/qlmaas/warnings.so
qat/qlmaas/wrappers.so
qat/qlmaas/auth/__init__.so
qat/qlmaas/auth/password.so
qat/qlmaas/auth/ssl.so
qlmaas/__init__.so
qlmaas/connection.so
qlmaas-1.12.3.data/scripts/qlmaas_prompt.py
qlmaas-1.12.3.data/scripts/qlmaas_test.py
qlmaas-1.12.3.dist-info/licenses/LICENSE.txt
qlmaas-1.12.3.dist-info/METADATA
qlmaas-1.12.3.dist-info/WHEEL
qlmaas-1.12.3.dist-info/top_level.txt
qlmaas-1.12.3.dist-info/RECORD
