Metadata-Version: 2.4
Name: qlmaas
Version: 1.12.3
Summary: Module qlmaas [caea168] - Compiled by Eviden
Home-page: https://atos.net/en/lp/myqlm
Author: Eviden Quantum Lab
Author-email: myqlm@atos.net
License: Eviden myQLM EULA
Project-URL: Documentation, https://myqlm.github.io
Project-URL: Bug Tracker, https://github.com/myQLM/myqlm-issues/issues
Project-URL: Community, https://myqlmworkspace.slack.com
Keywords: Quantum,myQLM,QLM,Atos,Eviden
Platform: Operating System :: Microsoft :: Windows
Classifier: Operating System :: Microsoft :: Windows
Classifier: Programming Language :: Python :: 3.9
Classifier: Topic :: Scientific/Engineering
Classifier: License :: Other/Proprietary License
License-File: LICENSE.txt
Requires-Dist: dill
Requires-Dist: prompt_toolkit
Requires-Dist: prettytable
Requires-Dist: pyOpenSSL
Requires-Dist: cffi
Requires-Dist: qat-hardware>=1.6.0
Requires-Dist: qat-quops>=1.5.0
Requires-Dist: packaging
Requires-Dist: websockets
Requires-Dist: qat-comm
Requires-Dist: qat-core
Requires-Dist: qat-hardware
Requires-Dist: qat-lang
Requires-Dist: qat-quops
Requires-Dist: qlmaas
Requires-Dist: qlmaas
Requires-Dist: qlmaas
Dynamic: author
Dynamic: author-email
Dynamic: classifier
Dynamic: description
Dynamic: description-content-type
Dynamic: home-page
Dynamic: keywords
Dynamic: license
Dynamic: license-file
Dynamic: platform
Dynamic: project-url
Dynamic: requires-dist
Dynamic: summary
